{
  "responseCode": 200,
  "message": "success",
  "title": "Setting Up Job Tickets",
  "description": "Configure custom fields and workflow settings for job tickets to track production details, specifications, and progress through your print shop workflow.",
  "content": {
    "20": {
      "defaultValue": "",
      "description": "",
      "hint": "",
      "inputTextMask": "",
      "labelAlign": "Auto",
      "maxsize": "",
      "name": "companysName20",
      "order": "1",
      "qid": "20",
      "readonly": "No",
      "required": "Yes",
      "size": "20",
      "subLabel": "",
      "text": "Print Shop Name",
      "type": "control_textbox",
      "validation": "None"
    },
    "21": {
      "cols": "40",
      "defaultValue": "",
      "description": "",
      "entryLimit": "None-0",
      "entryLimitMin": "None-0",
      "hint": "",
      "labelAlign": "Auto",
      "maxsize": "",
      "mde": "Yes",
      "name": "pleaseAdd",
      "order": "8",
      "qid": "21",
      "readonly": "No",
      "required": "No",
      "rows": "6",
      "subLabel": "",
      "text": "Please add any additional information or click Submit below.",
      "type": "control_textarea",
      "validation": "None",
      "wysiwyg": "Disable"
    },
    "41": {
      "calcValues": "",
      "description": "",
      "labelAlign": "Auto",
      "name": "wouldYou41",
      "options": "Yes|No",
      "order": "7",
      "qid": "41",
      "readonly": "No",
      "required": "Yes",
      "selected": "",
      "text": "Would you like to add the Custom Fields on your own?",
      "type": "control_yesno"
    },
    "44": {
      "compoundHint": "",
      "description": "",
      "labelAlign": "Auto",
      "middle": "No",
      "name": "ltspanStylefontsize",
      "order": "2",
      "prefix": "No",
      "prefixChoices": "",
      "qid": "44",
      "readonly": "No",
      "required": "Yes",
      "sublabels": {
        "prefix": "Prefix",
        "first": "First Name",
        "middle": "Middle Name",
        "last": "Last Name",
        "suffix": "Suffix"
      },
      "suffix": "No",
      "text": "Print Shop Administrator Full Name",
      "type": "control_fullname"
    },
    "46": {
      "compoundHint": "",
      "countryCode": "No",
      "description": "",
      "inputMask": "disable",
      "inputMaskValue": "(###) ###-####",
      "labelAlign": "Auto",
      "name": "administratorPhone",
      "order": "4",
      "qid": "46",
      "readonly": "No",
      "required": "Yes",
      "sublabels": {
        "country": "Country Code",
        "area": "Area Code",
        "phone": "Phone Number",
        "full": "Phone Number",
        "masked": ""
      },
      "text": "Administrator Phone Number",
      "type": "control_phone"
    },
    "47": {
      "allowCustomDomains": "No",
      "allowedDomains": "",
      "confirmation": "No",
      "confirmationHint": "example@example.com",
      "confirmationSublabel": "Confirm Email",
      "defaultValue": "",
      "description": "",
      "disallowFree": "No",
      "domainCheck": "No",
      "hint": "",
      "labelAlign": "Auto",
      "maxsize": "",
      "name": "printShop",
      "order": "3",
      "qid": "47",
      "readonly": "No",
      "required": "Yes",
      "size": "30",
      "subLabel": "example@example.com",
      "text": "Print Shop Administrator Email",
      "type": "control_email",
      "validation": "Email",
      "verificationCode": "No"
    },
    "66": {
      "autoFixed": "No",
      "cols": "648",
      "defaultValue": "",
      "description": "",
      "entryLimit": "None-0",
      "entryLimitMin": "None-0",
      "hint": "",
      "labelAlign": "Auto",
      "maxsize": "",
      "mde": "Yes",
      "name": "pleaseEnter",
      "order": "6",
      "qid": "66",
      "readonly": "No",
      "required": "Yes",
      "rows": "163",
      "subLabel": "",
      "text": "Please enter your job ticket custom fields below and indicate whether each should be a Single Line Text, Paragraph, Dropdown, Date, or File Upload.",
      "type": "control_textarea",
      "validation": "None",
      "wysiwyg": "Disable"
    },
    "67": {
      "boxAlign": "Left",
      "builderDescription": "",
      "builderLabel": "YouTube",
      "cfname": "YouTube",
      "customCSS": "",
      "fieldParameters": "[{\"order\":\"0\",\"parentID\":\"5273bb4faa80af0979000006\",\"name\":\"URL\",\"readable\":\"URL\",\"paramStatus\":\"enabled\",\"type\":\"text\",\"default\":\"https:\\/\\/youtu.be\\/jO1lndiGs1c\",\"tip\":\"<p><br /><\\/p>\"}]</p>",
      "finalSrc": "",
      "frameHeight": "350",
      "frameSrc": "",
      "frameWidth": "650",
      "inlineEditDefaultValue": "Type a question",
      "label": "Yes",
      "labelAlign": "Top",
      "maxWidth": "587",
      "name": "typeA67",
      "order": "5",
      "paramChunks": "",
      "qid": "67",
      "required": "No",
      "selectedField": "5273bb4faa80af0979000005",
      "settingNames": "URL,customCSS",
      "settingNamesCSS": "",
      "static": "Yes",
      "text": "Please watch the introductory video below on how to add custom fields to your job ticket before proceeding:",
      "type": "control_widget",
      "URL": "https://youtu.be/wWaVxM-2caY",
      "widgetTabs": "[[\"general\",\"settingNames\"],[\"customcss\",\"settingNamesCSS\"]]",
      "widgetType": "widget"
    }
  },
  "duration": "85.24ms",
  "info": null,
  "limit-left": 9981
}
